cjm_psl_utils/__init__.py
cjm_psl_utils/_modidx.py
cjm_psl_utils/core.py
cjm_psl_utils-0.0.4.dist-info/LICENSE
cjm_psl_utils-0.0.4.dist-info/METADATA
cjm_psl_utils-0.0.4.dist-info/WHEEL
cjm_psl_utils-0.0.4.dist-info/entry_points.txt
cjm_psl_utils-0.0.4.dist-info/top_level.txt
cjm_psl_utils-0.0.4.dist-info/RECORD
