Metadata-Version: 2.1
Name: cjm-psl-utils
Version: 0.0.4
Summary: Some utility functions using the Python Standard Library.
Home-page: https://github.com/cj-mills/cjm-psl-utils
Author: cj-mills
Author-email: millscj.mills2@gmail.com
License: Apache Software License 2.0
Keywords: nbdev jupyter notebook python
Classifier: Development Status :: 4 - Beta
Classifier: Intended Audience :: Developers
Classifier: Natural Language :: English
Classifier: Programming Language :: Python :: 3.9
Classifier: Programming Language :: Python :: 3.10
Classifier: License :: OSI Approved :: Apache Software License
Requires-Python: >=3.9
License-File: LICENSE
Requires-Dist: tqdm
Provides-Extra: dev
